{
  "lastRunAt": "2026-06-24T05:45:32.001Z",
  "elapsedSeconds": 3.4,
  "files": {
    "marketQuotes.json": {
      "count": 36,
      "ms": 655,
      "bytes": 6869
    },
    "commodityQuotes.json": {
      "count": 10,
      "ms": 13,
      "bytes": 1840
    },
    "cryptoQuotes.json": {
      "count": 13,
      "ms": 2417,
      "bytes": 2156
    },
    "sectors.json": {
      "count": 20,
      "ms": 328,
      "bytes": 1666
    }
  },
  "sources": {
    "stocks": "Sina hq.sinajs.cn + Tencent qt.gtimg.cn",
    "commodities": "Sina hq.sinajs.cn hf_*/nf_*/fx_*",
    "crypto": "Gate.io api.gateio.ws /api/v4/spot/tickers",
    "sectors": "Eastmoney push2.eastmoney.com clist/get"
  }
}