{
  "generated_at": "2026-07-10T16:52:11",
  "kanban": {
    "backlog": [
      {
        "ID": "SAT-007",
        "Task": "Create first CubeSat exploded-view part list",
        "Type": "3D Content",
        "Owner": "TBD",
        "Links": "SAT-006"
      },
      {
        "ID": "SAT-008",
        "Task": "Choose 10 seed real satellites for the atlas",
        "Type": "Data",
        "Owner": "TBD",
        "Links": "ROADMAP Phase 1, DEC-003"
      },
      {
        "ID": "SAT-009",
        "Task": "Design beginner/adult/engineering explanation schema",
        "Type": "Curriculum",
        "Owner": "TBD",
        "Links": "SAT-006"
      },
      {
        "ID": "SAT-010",
        "Task": "Select orbit calculation stack for MVP",
        "Type": "Engineering",
        "Owner": "TBD",
        "Links": "DEC-001, DEC-004"
      },
      {
        "ID": "SAT-011",
        "Task": "Draft classroom challenge format",
        "Type": "Learning Design",
        "Owner": "TBD",
        "Links": "ROADMAP Phase 2"
      },
      {
        "ID": "SAT-012",
        "Task": "Define safety boundary for public satellite data use",
        "Type": "Policy",
        "Owner": "TBD",
        "Links": "README rules, DEC-002"
      }
    ],
    "next": [
      {
        "ID": "SAT-002",
        "Task": "Build source inventory",
        "Type": "Research",
        "Owner": "TBD",
        "Exit Criteria": "Each source has URL, use case, license/terms note, and data fields"
      },
      {
        "ID": "SAT-003",
        "Task": "Define app information architecture",
        "Type": "Product",
        "Owner": "TBD",
        "Exit Criteria": "Main screens and navigation are documented"
      }
    ],
    "in_progress": [
      {
        "ID": "SAT-001",
        "Task": "Lock MVP scope",
        "Type": "Product",
        "Owner": "Patrick (review)",
        "Started": "2026-07-08",
        "Notes": "DEC-004 tech stack accepted; DEC-003 picks awaiting JWST/Starlink call"
      },
      {
        "ID": "SAT-006",
        "Task": "Define canonical satellite subsystem taxonomy",
        "Type": "Curriculum",
        "Owner": "Patrick (review)",
        "Started": "2026-07-08",
        "Notes": "Inline v0.1 embedded in mvp.html per DEC-005; full SAT-006 doc to follow"
      }
    ],
    "review": [
      {
        "ID": "None",
        "Task": "No pending review",
        "Type": "-",
        "Reviewer": "-",
        "Review Need": "-"
      }
    ],
    "done": [
      {
        "ID": "SAT-000",
        "Task": "Define product direction",
        "Type": "Product",
        "Completed": "2026-07-08",
        "Evidence": "App concept: exploded 3D satellite education lab, real satellite atlas, orbit demo, design sandbox"
      },
      {
        "ID": "SAT-004",
        "Task": "Set up project tracking board",
        "Type": "Project Ops",
        "Completed": "2026-07-08",
        "Evidence": "Initial board, logs, templates, local git repo, and rollback checkpoint"
      },
      {
        "ID": "SAT-005",
        "Task": "Validate project tracking workflow",
        "Type": "Project Ops",
        "Completed": "2026-07-08",
        "Evidence": "User accepted the 7-file tracking system (ROADMAP/KANBAN/LOGBOOK/CHANGES/FEEDBACK/DECISIONS/ROLLBACK) + ID-prefix cross-link + 3-level rollback + parser-driven dashboard. No changes requested."
      }
    ]
  },
  "phases": [
    {
      "title": "Phase 0: Project Tracking Foundation",
      "goal": "Make the project trackable before implementation starts.",
      "exit_criteria": [
        "Project board exists.",
        "Feedback, change, decision, logbook, and rollback files exist.",
        "Every future task can be linked to a stable ID."
      ],
      "initial_tasks": [
        "SAT-004: Set up project tracking board.",
        "SAT-005: Validate project tracking workflow."
      ],
      "phase_num": 0
    },
    {
      "title": "Phase 1: Educational Knowledge Base",
      "goal": "Convert public resources into a structured educational model.",
      "exit_criteria": [
        "Canonical subsystem taxonomy is defined.",
        "Source inventory covers books, videos, databases/websites, and GitHub tools.",
        "10 real satellite examples are selected.",
        "Explanation schema supports beginner, adult, and engineering levels."
      ],
      "initial_tasks": [],
      "phase_num": 1
    },
    {
      "title": "Phase 2: MVP Interaction Design",
      "goal": "Define the first usable app experience.",
      "exit_criteria": [
        "Main screens are specified.",
        "CubeSat exploded-view interaction is described.",
        "Satellite atlas card layout is specified.",
        "Orbit demo behavior is specified.",
        "\"Design your own satellite\" MVP rules are specified."
      ],
      "initial_tasks": [],
      "phase_num": 2
    },
    {
      "title": "Phase 3: Prototype Build",
      "goal": "Build a working browser prototype.",
      "exit_criteria": [
        "One 3D CubeSat model can expand/collapse.",
        "Parts are selectable and show educational explanations.",
        "10 satellite atlas entries are browsable.",
        "A basic orbit visualization demonstrates LEO, MEO, GEO, and SSO.",
        "Prototype runs locally."
      ],
      "initial_tasks": [],
      "phase_num": 3
    },
    {
      "title": "Phase 4: Classroom Mode",
      "goal": "Turn the prototype into a teaching tool.",
      "exit_criteria": [
        "Teacher flow exists.",
        "Student challenge flow exists.",
        "At least 3 challenge prompts exist.",
        "Exportable student design report exists."
      ],
      "initial_tasks": [],
      "phase_num": 4
    },
    {
      "title": "Phase 5: Data and Simulation Upgrade",
      "goal": "Add real data and more accurate orbital/engineering behavior.",
      "exit_criteria": [
        "CelesTrak TLE ingestion is implemented.",
        "Satellite metadata schema is stable.",
        "Design sandbox includes simple mass, power, orbit, and communications checks.",
        "Data sources and update dates are shown in the app."
      ],
      "initial_tasks": [],
      "phase_num": 5
    }
  ],
  "logbook": [
    {
      "id": "LOG-001",
      "title": "Project tracking system created",
      "date": "2026-07-08",
      "related_tasks": "SAT-004, SAT-005",
      "status": "Completed for initial setup; awaiting user review",
      "summary": "Created a file-based project board with kanban, roadmap, feedback",
      "evidence": [],
      "next_action": "User reviews the workflow and asks for adjustments if needed."
    },
    {
      "id": "LOG-002",
      "title": "First rollback checkpoint created",
      "date": "2026-07-08",
      "related_tasks": "SAT-004",
      "status": "Completed",
      "summary": "Initialized a local git repository and committed the initial project",
      "evidence": [],
      "next_action": "Future task completions should be committed and recorded in"
    },
    {
      "id": "LOG-003",
      "title": "SAT-005 user review — accepted as-is",
      "date": "2026-07-08",
      "related_tasks": "SAT-005",
      "status": "Accepted",
      "summary": "User confirmed the 7-file tracking workflow (ROADMAP / KANBAN / LOGBOOK",
      "evidence": [],
      "next_action": "Start SAT-006 (real data ingest: CelesTrak GP JSON + TLE) — the"
    },
    {
      "id": "LOG-004",
      "title": "SAT-001 MVP scope draft v0.1",
      "date": "2026-07-08",
      "related_tasks": "SAT-001",
      "status": "In Progress, awaiting user review",
      "summary": "Drafted DEC-003 MVP scope v0.1 — 1U CubeSat reference model + 10",
      "evidence": [],
      "next_action": "User reviews DEC-003 picks (especially JWST L2 and Starlink"
    },
    {
      "id": "LOG-005",
      "title": "DEC-004 MVP tech stack locked",
      "date": "2026-07-08",
      "related_tasks": "SAT-001 (sub-decision)",
      "status": "In Progress, awaiting user accept/change",
      "summary": "Picked tech stack for Phase 3 Prototype Build — single-file HTML",
      "evidence": [],
      "next_action": "User reviews DEC-004 stack choice. If accepted, proceed to"
    },
    {
      "id": "LOG-006",
      "title": "Phase 3 build kicked off — mvp.html skeleton v0.1",
      "date": "2026-07-08",
      "related_tasks": "SAT-001, SAT-006, SAT-007 (partial), SAT-008 (partial)",
      "status": "In Progress",
      "summary": "Built first cut of `mvp.html` — single-file HTML with 4 tabs",
      "evidence": [],
      "next_action": "User opens `mvp.html` in browser, validates 4 tabs render"
    }
  ],
  "feedback": [
    {
      "ID": "FB-001",
      "Date": "2026-07-08",
      "Source": "User",
      "Feedback": "Build a trackable project board. Every completed phase or small goal must be recorded. Every feedback and modification must leave records for rollback.",
      "Status": "Addressed",
      "Linked Changes": "CHG-001"
    },
    {
      "ID": "FB-002",
      "Date": "2026-07-08",
      "Source": "Dashboard parser",
      "Feedback": "\"Project board items disappeared from the dashboard\" — `dashboard_data.json` showed `goal: \"\"` and 0 items for every project because `build_dashboard_v2.py` regex required `**bold**` `Goal` / `Exit criteria` / `Initial tasks` / `Evidence` headings but the project boards used plain headings.",
      "Status": "Addressed",
      "Linked Changes": "CHG-003"
    }
  ],
  "changes": [
    {
      "ID": "CHG-001",
      "Date": "2026-07-08",
      "Related Task": "SAT-004",
      "Related Feedback": "FB-001",
      "Change": "Created the initial project tracking board and documentation structure.",
      "Files/Areas Affected": "Project board Markdown files",
      "Rollback": "Revert initial project-board files or restore from the first git checkpoint"
    },
    {
      "ID": "CHG-002",
      "Date": "2026-07-08",
      "Related Task": "SAT-004",
      "Related Feedback": "FB-001",
      "Change": "Initialized local git versioning and recorded the first rollback checkpoint.",
      "Files/Areas Affected": "Git repository metadata, `ROLLBACK.md`, `LOGBOOK.md`, `KANBAN.md`",
      "Rollback": "Revert the checkpoint-record update commit; keep or remove `.git` depending on whether version history is still needed"
    },
    {
      "ID": "CHG-003",
      "Date": "2026-07-08",
      "Related Task": "SAT-006",
      "Related Feedback": "FB-002",
      "Change": "Fixed the `Goal` / `Exit criteria` / `Initial tasks` / `Evidence` regex in `build_dashboard_v2.py` so it matches plain (non-`**bold**`) project-board headings, and made all four regexes accept either bold or plain form via `(?: \\*\\*)?` while tolerating leading indent on bullets. This is why `dashboard_data.json` had `goal: \"\"` and zero items for every project in v1. Added 4 entries / 9 sections / 6 phases back into the dashboard. Also added `lang=\"zh-CN\"` + EN ↔ 中 toggle button + `data-i18n` attribute scaffolding (`pageTitle`, `appName`, `tagline`, `generated` prefix) in v2.",
      "Files/Areas Affected": "`build_dashboard_v2.py` (lines ~85-138), `dashboard.html` (head + header + `templates/i18n.js` not yet wired), `dashboard_data.json` (rebuilt with full content), new file `build_dashboard_v2.py.sv` saved before v1 and v2 writes",
      "Rollback": "Restore `.bak` and `.sv` files, run `python3 build_dashboard.py` instead of v2 to confirm v1 produces the old (broken) shape, or revert commit"
    },
    {
      "ID": "CHG-004",
      "Date": "2026-07-08",
      "Related Task": "SAT-005",
      "Related Feedback": "(this CHG itself)",
      "Change": "User accepted the 7-file tracking workflow as-is. Workflow baseline frozen: 7-file structure (ROADMAP / KANBAN / LOGBOOK / CHANGES / FEEDBACK / DECISIONS / ROLLBACK) + ID-prefix cross-link convention (SAT-/LOG-/CHG-/FB-/DEC-/RB-) + 3-level rollback (RB-001 to RB-004) + parser-driven dashboard confirmed as the project's working contract. SAT-005 moved from Review → Done.",
      "Files/Areas Affected": "`KANBAN.md` (SAT-005 row in Done), `LOGBOOK.md` (LOG-003), `CHANGES.md` (this row), `FEEDBACK.md` (FB-001 will follow)",
      "Rollback": "Move SAT-005 back to Review in `KANBAN.md` and reverse the rows; no data/asset/code changes happened"
    },
    {
      "ID": "CHG-005",
      "Date": "2026-07-08",
      "Related Task": "SAT-005 (audit follow-up)",
      "Related Feedback": "FB-002",
      "Change": "Fixed incomplete CHG-003 fix: parser regex leading `**` group changed from `(?:\\*\\*)` (mandatory) to `(?:\\*\\*)?` (optional) so plain `Goal:` / `Exit criteria:` / `Initial tasks:` headings in `ROADMAP.md` actually match. Also removed duplicate `<button id=\"lang-toggle\">` (the second one inside `<span class=\"meta\">` was non-functional because `getElementById` only returns the first match). Phase 0-5 now each show 1 goal + 4-5 exit criteria in the dashboard.",
      "Files/Areas Affected": "`build_dashboard_v2.py` (phase regex lines), `dashboard.html` (regenerated), `dashboard_data.json` (rebuilt with full phase content)",
      "Rollback": "`git revert <commit>` (RB-005)"
    },
    {
      "ID": "CHG-006",
      "Date": "2026-07-08",
      "Related Task": "SAT-001",
      "Related Feedback": "(this CHG itself)",
      "Change": "Locked MVP scope draft v0.1 in DEC-003: 1U CubeSat reference model + 10 atlas entries (ISS / Hubble / JWST / Starlink v2 mini / GPS III / GOES-18 / Sentinel-2 / Landsat-9 / NOAA-20 / 1U CubeSat) + LEO/MEO/GEO/SSO orbit visual demo (no SGP4 in MVP per DEC-001) + 1U design sandbox stub (educational budget only per DEC-002). SAT-001 moved Next → In Progress with Patrick listed as reviewer.",
      "Files/Areas Affected": "`DECISIONS.md` (DEC-003 row), `KANBAN.md` (SAT-001 row), `LOGBOOK.md` (LOG-004 row), `dashboard.html` (regenerated to reflect new kanban state)",
      "Rollback": "Move SAT-001 back to Next in `KANBAN.md`, remove DEC-003 from `DECISIONS.md`, remove LOG-004 from `LOGBOOK.md`"
    },
    {
      "ID": "CHG-007",
      "Date": "2026-07-08",
      "Related Task": "SAT-001 (sub-decision)",
      "Related Feedback": "(this CHG itself)",
      "Change": "Locked MVP tech stack in DEC-004: single-file HTML + three.js (CDN) + raw CSS + vanilla JS. Rejected React/Vite/Vue for setup overhead; rejected Web Components for ergonomic tax at this scale. 3D CubeSat model uses primitive geometry (Box/Cylinder) — no GLTF needed. Deploy path = same `cp` as dashboard.html.",
      "Files/Areas Affected": "`DECISIONS.md` (DEC-004 row), `LOGBOOK.md` (LOG-005 row), `dashboard.html` (regenerated)",
      "Rollback": "Remove DEC-004 from `DECISIONS.md`, remove LOG-005 from `LOGBOOK.md`, no code/data changes happened"
    },
    {
      "ID": "CHG-008",
      "Date": "2026-07-08",
      "Related Task": "SAT-001 + SAT-006 + SAT-007 (partial) + SAT-008 (partial)",
      "Related Feedback": "(this CHG itself)",
      "Change": "Built `mvp.html` v0.1 skeleton per DEC-004 + DEC-005. Single-file HTML, 4 tabs (CubeSat / Atlas / Orbit / Sandbox), three.js scene with 1U CubeSat primitive geometry, atlas cards listing 10 satellites from DEC-003 (placeholder data), orbit viz with Earth + 3 rings (LEO/MEO/GEO; SSO highlighted separately), sandbox form (subsystem selectors, no budget calc yet). DEC-005 inline subsystem taxonomy (6 subsystems + 1 payload slot). SAT-006 → In Progress; SAT-001 stays In Progress pending DEC-003 ⚠️ pick confirm.",
      "Files/Areas Affected": "`mvp.html` (new, ~22 KB), `DECISIONS.md` (DEC-005), `KANBAN.md` (SAT-006 row), `LOGBOOK.md` (LOG-006), `dashboard.html` (regenerated)",
      "Rollback": "`git revert <this-commit>` then delete `mvp.html`"
    },
    {
      "ID": "CHG-009",
      "Date": "2026-07-09",
      "Related Task": "SAT-005 (audit follow-up)",
      "Related Feedback": "(this CHG itself)",
      "Change": "Polish round 1: TDZ fix (hoist let declarations above setTab), `lookAt(0,0,0)` on all 3 cameras, dedupe `initCube()` double-call, fixed CubeSat click/explode/reset interactions, sandbox camera distance + FOV. Plus Phase 3 polish: 7 subsystem description cards (mass/power/function/spec/example) with click-sync between 3D and panel, 2-column layout, procedural canvas textures for solar panels (cell grid), PCB green for OBC, thermal fins, antenna feed horn, payload camera lens. 3-light setup (key/fill/rim). Idle rotation.",
      "Files/Areas Affected": "`mvp.html` (RB-009..014 series), `DECISIONS.md` (DEC-004), `LOGBOOK.md` (LOG-007+), `dashboard.html` (regenerated)",
      "Rollback": "`git revert <commit>` for any of RB-009..014"
    },
    {
      "ID": "CHG-010",
      "Date": "2026-07-09",
      "Related Task": "SAT-002 (source inventory) + DEC-001 follow-up",
      "Related Feedback": "(this CHG itself)",
      "Change": "Polish round 2 — `all 3` (Atlas real data + i18n modal + live ISS): (1) 10 atlas cards now have real Wikipedia-sourced mass/power/agency/year/mission/wiki URL. ISS 419.7 t, Hubble 11.1 t, JWST 6.2 t, Starlink v2 mini 800 kg, GPS III 2.2 t, GOES-18 5.2 t, Sentinel-2 1.1 t, Landsat-9 2.7 t, NOAA-20 2.5 t, 1U CubeSat 1 kg. (2) Atlas modal full i18n — added `atlasAgency/Orbit/Alt/Mass/Power/Year/Mission/Source` keys zh+en, replaced inline `isZh ? '机构' : 'Agency'` with `t()` calls. Cards re-render on language toggle. (3) Live ISS position via CelesTrak GP (NORAD 25544) — orange emissive dot moves on LEO ring using simple Keplerian advancement from EPOCH + mean motion. HUD shows `🛰️ ISS live (CelesTrak YYYY-MM-DDTHH:MMZ)`. Refresh every 30 min. **No SGP4** per DEC-001 staged approach — Keplerian mean-anomaly advancement is enough for visual demo. (4) Modal also has Wikipedia source link in new section.",
      "Files/Areas Affected": "`mvp.html` (ATLAS data + i18n + orbit live), `I18N` (8 new keys zh+en), `dashboard.html` (regenerated)",
      "Rollback": "`git revert <this-commit>`"
    },
    {
      "ID": "CHG-011",
      "Date": "2026-07-09",
      "Related Task": "SAT-005 (audit follow-up)",
      "Related Feedback": "(this CHG itself)",
      "Change": "Polish round 3 — realistic 1U CubeSat: 27 parts (was 7), 4 corner rails (anodized aluminum with mounting holes), 4 deployable monopole antennas, star tracker baffle + RBF pin + 4 sun sensors + 3 magnetorquer coils + 2 Kapton heater strips, payload camera on -Z. Plus: per-satellite distinct 3D models in atlas modal — ISS with 6 modules + Canadarm2 + Cupola, GPS III with L-shaped solar wings + L-band antenna array, GOES-18 with ABI imager + magnetometer boom, JWST with 19 hex mirror segments (with visible gaps) + backplane + fine guidance sensor, Starlink with star tracker + antennas, Sentinel-2 with MSI + radiator, Landsat-9 with TIRS + OLI dual instruments, NOAA-20 with VIIRS + CrIS. 4 archetype generators (iss/hubble/jwst/starlink) + 5 specialized (gps/goes/sentinel2/landsat/noaa20) + generic boxSat + cube1u. `highlightPart()` pulses ALL parts sharing same sub-system name. Modal lighting upgraded to 3-light sun setup (key 1.4, fill 0.35, rim 0.18) for sharper shadows. ISS got Soyuz + Dragon docking vehicles.",
      "Files/Areas Affected": "`mvp.html` (SAT_ARCH), `I18N` (no new keys), procedural models",
      "Rollback": "`git revert RB-016` reverts realistic 1U; `git revert RB-018` reverts per-satellite models"
    },
    {
      "ID": "CHG-012",
      "Date": "2026-07-09",
      "Related Task": "(DEC follow-up)",
      "Related Feedback": "(this CHG itself)",
      "Change": "Atlas modal 3D preview framework: built `generateSatModel(sat)` switch routing 10 satellites to specialized generators, `loadSatGLB(sat)` with 404-fallback to procedural, `exportToGLB(group)` for testing pipeline. Added `getSatGLBUrl(sat)` pattern (slug from sat.id). Created `models/` directory with README.md documenting Meshy.ai / Tripo3D / TripoSR / Hunyuan3D / Luma / Rodin integration steps and file naming convention. Modal shows status badge: `🛰 GLB model` if loaded from URL, `⚙ procedural` otherwise. Tested export→reload cycle: GLTFExporter writes binary GLB blob, GLTFLoader reads it back successfully. **Pipeline ready for Patrick to drop Meshy-generated GLBs in `models/sat-{slug}.glb`.**",
      "Files/Areas Affected": "`mvp.html` (generateSatModel, loadSatGLB, exportToGLB), `models/README.md`",
      "Rollback": "`git revert RB-019`"
    },
    {
      "ID": "CHG-013",
      "Date": "2026-07-09",
      "Related Task": "SAT-005 (audit follow-up)",
      "Related Feedback": "(this CHG itself)",
      "Change": "Orbit demo upgraded from single-line rings to **altitude band ranges** per DEC-003. Each orbit type (LEO 300-1500, MEO 5000-25000, GEO 35500-36100, SSO 600-900 km) is now rendered as 2 boundary rings + translucent fill between. Added canvas sprite labels per sample satellite with orbit-color background pill. `sampleGroup` sub-group auto-rotates dots + labels with the band, fixing manual rotation math for SSO tilt. Removed old orbit-name sprite labels (replaced by per-sample names).",
      "Files/Areas Affected": "`mvp.html` (ORBITS array altMin/altMax), `dashboard.html` (regenerated)",
      "Rollback": "`git revert RB-021` (band) or `git revert RB-022` (labels)"
    },
    {
      "ID": "CHG-014",
      "Date": "2026-07-09",
      "Related Task": "(DEC follow-up)",
      "Related Feedback": "(this CHG itself)",
      "Change": "NASA reference photos integrated into atlas modal. Searched `images-api.nasa.gov` (NASA official image API) for each of 10 satellites, got real iconic photos (ISS spacewalk, JWST deployment, GOES-R transport, etc.). Added `nasaImageId` field to each ATLAS entry + `nasaImageUrl(id, size)` helper. Modal now shows real NASA photo below 3D model (max-height 120px thumbnail, clickable to open full-size on NASA Images). Total 10 satellite-image pairs verified. **Note: NASA's 3D Resources API moved to science.nasa.gov/3d-resources/ but has no JSON API — could not auto-discover GLB URLs. Pipeline (RB-019) ready for Patrick to drop manual GLBs.**",
      "Files/Areas Affected": "`mvp.html` (nasaImageId fields, modal HTML), `models/README.md` (updated with NASA image sourcing note)",
      "Rollback": "`git revert RB-023`"
    },
    {
      "ID": "CHG-015",
      "Date": "2026-07-09",
      "Related Task": "SAT-005 (audit follow-up)",
      "Related Feedback": "(this CHG itself)",
      "Change": "NASA photo thumbnail polish: changed modal layout from full-width photo to 16:9 thumbnail (max-height 120px) with `aspect-ratio` + `object-fit: cover`. Image wrapped in `<a href=\"https://images.nasa.gov/details-{id}\">` so click opens full-size on NASA Images. Hover: scale(1.02) + accent border + soft shadow. Modal flow more compact. Also backfilled CHG-009..014 entries in CHANGES.md with full audit trail (What/Why/Tasks/Feedback/Files/Rollback) for all RB-* commits that weren't documented at commit time.",
      "Files/Areas Affected": "`mvp.html` (.nasa-photo CSS), `CHANGES.md` (6 new rows)",
      "Rollback": "`git revert RB-024`"
    },
    {
      "ID": "CHG-016",
      "Date": "2026-07-09",
      "Related Task": "(DEC follow-up)",
      "Related Feedback": "(this CHG itself)",
      "Change": "Sandbox 3D preview reactive: rewrote `updateSandboxPreview()` so ALL 5 dropdowns drive real 3D changes (not just EPS+ADCS). EPS: 0/4/8 panels (body/deploy/gauntlet + wing tips + booms). OBC: 3 board sizes (arm-c0 small / arm-a53 + SOIC chip / SoC + heat sink + fins + 2nd chip). ADCS: 0/3 magnetorquer tori/3 reaction wheels + star tracker. Comms: UHF whip / S-band patch+dipole / X-band dish on boom. Payload: camera (body+hood+lens) / IoT (box+LoRa whip) / SSR (long box+dipole) / AIS (pink box+long VHF whip). Budget formula reworked to per-subsystem mass/power lookup tables. Mission-fit detection expanded to 5 modes (EO imaging / IoT store-and-fwd / Maritime tracking / Ham radio relay / Over 1U mass limit). Added OrbitControls in sandbox so user can drag-rotate + scroll-zoom; auto-rotation continues while idle.",
      "Files/Areas Affected": "`mvp.html` (updateSandboxPreview rewrite, initSandbox + sbControls)",
      "Rollback": "`git revert RB-025` reverts sandbox 3D; `git revert RB-026` reverts controls"
    },
    {
      "ID": "CHG-017",
      "Date": "2026-07-09",
      "Related Task": "(DEC follow-up)",
      "Related Feedback": "(this CHG itself)",
      "Change": "Sandbox budget transparency: replaced single-line mass/power numbers with per-subsystem breakdown rows showing which subsystem contributes how much. Each row has a dotted-underline hover hint and `title=` tooltip explaining the calculation (e.g., \"0.55 kg = 4 main + 4 tip + 4 booms",
      "Files/Areas Affected": "11 W = 8 × 1.2 W peak + battery 2 W\"). All 14 tooltips (6 mass + 5 power + 1 structure) translated to zh + en, sourced from real CubeSat product specs (Pumpkin Kit, ISIS iOBC, EnduroSat EPS, BlueCanyon XACT). New sources row at bottom: \"**Sources:** Pumpkin Kit / ISIS iOBC / EnduroSat EPS / BlueCanyon XACT (educational estimates, not engineering validation)\". DEC-002 compliance: still no real engineering validation, all values are educational lookup tables.",
      "Rollback": "`mvp.html` (.bd-breakdown CSS, buildBDWithTip + tip object)"
    },
    {
      "ID": "CHG-018",
      "Date": "2026-07-09",
      "Related Task": "SAT-005 (audit follow-up)",
      "Related Feedback": "(this CHG itself)",
      "Change": "3D CubeSat hover-pick sync: added mousemove + mouseleave handlers to 3D canvas. Hovering over a 3D part now highlights the matching sub-card in the right panel (transient, not persistent). Hovering a sub-card pulses the matching 3D part(s) with a 1.12x scale animation. Click remains the persistent selection. Refactored click handler to use shared `pickAt()` function. Added `.sub-card:hover` border + box-shadow for clearer hover state.",
      "Files/Areas Affected": "`mvp.html` (initCube hover + pickAt + pulsePart + delegated sub-card hover)",
      "Rollback": "`git revert RB-028`"
    },
    {
      "ID": "CHG-019",
      "Date": "2026-07-09",
      "Related Task": "(audit follow-up)",
      "Related Feedback": "(this CHG itself)",
      "Change": "ROLLBACK.md backfill: full checkpoint table for all 28 RB-* commits with date / scope / CHG / git commit / rollback command columns. Replaced the previous 7-row table that was split between the main section and the Rollback Levels section (RB-008 was misplaced).",
      "Files/Areas Affected": "`ROLLBACK.md` (rewritten checkpoint table)",
      "Rollback": "`git revert RB-029` reverts ROLLBACK.md (but you lose the rollback chain — only do this in emergencies)"
    }
  ],
  "decisions": [
    {
      "id": "DEC-001",
      "title": "Use a staged technical approach for orbital computation",
      "date": "2026-07-08",
      "status": "Proposed",
      "context": "The app needs orbit education early, but high-fidelity simulation can",
      "decision": "Start with simple visual orbit categories in the MVP. Add CelesTrak",
      "consequences": "MVP remains buildable quickly, while the architecture still"
    },
    {
      "id": "DEC-002",
      "title": "Use public educational abstraction for satellite internals",
      "date": "2026-07-08",
      "status": "Proposed",
      "context": "The goal is education, not exposing sensitive spacecraft control or",
      "decision": "Model spacecraft using public subsystem concepts and representative",
      "consequences": "The app can teach engineering concepts safely while still being"
    },
    {
      "id": "DEC-003",
      "title": "MVP scope v0.1 (draft for SAT-001)",
      "date": "2026-07-08",
      "status": "Proposed — awaiting user accept/change",
      "context": "Phase 3 exit criteria require 1 3D CubeSat model, 10 atlas entries,",
      "decision": "",
      "consequences": "Prototype ships in single browser HTML with 4 main screens"
    },
    {
      "id": "DEC-004",
      "title": "MVP tech stack — single-file HTML + three.js + raw CSS",
      "date": "2026-07-08",
      "status": "Proposed — awaiting user accept/change",
      "context": "Phase 3 Prototype Build needs a runtime. Options considered:",
      "decision": "Single-file HTML + three.js (CDN, e.g. `three@0.160` via",
      "consequences": "MVP ships as one HTML file Patrick can open locally with"
    },
    {
      "id": "DEC-005",
      "title": "Canonical subsystem taxonomy v0.1 (inline in mvp.html)",
      "date": "2026-07-08",
      "status": "Proposed — embedded in mvp.html as JS object; full SAT-006 doc to follow",
      "context": "3D CubeSat model + atlas cards share a common vocabulary. Without a",
      "decision": "",
      "consequences": "Atlas cards and 3D CubeSat parts both reference this"
    }
  ],
  "checkpoints": [
    {
      "Checkpoint": "RB-001",
      "Date": "2026-07-08",
      "Scope": "Initial project board + parser fix + i18n shell",
      "Related Changes": "CHG-001 + CHG-003",
      "Git Commit": "`881addf`",
      "Rollback Command": "`git revert 881addf`"
    },
    {
      "Checkpoint": "RB-002",
      "Date": "2026-07-08",
      "Scope": "CHG-003: Add v1-initial + v2-parser-fix snapshots + bump .gitignore",
      "Related Changes": "CHG-003",
      "Git Commit": "`cd52fab`",
      "Rollback Command": "`git revert cd52fab`"
    },
    {
      "Checkpoint": "RB-003",
      "Date": "2026-07-08",
      "Scope": "ROLLBACK.md checkpoint table: fill RB-001 + RB-002 real hashes; fix RB-001 scope",
      "Related Changes": "CHG-003 (meta)",
      "Git Commit": "`5a5c0da`",
      "Rollback Command": "`git revert 5a5c0da`"
    },
    {
      "Checkpoint": "RB-004",
      "Date": "2026-07-08",
      "Scope": "SAT-005 baseline freeze: KANBAN → Done + LOG-003 + FB-002 + regenerated dashboard",
      "Related Changes": "CHG-004 + FB-002",
      "Git Commit": "`e349860`",
      "Rollback Command": "`git revert e349860`"
    },
    {
      "Checkpoint": "RB-005",
      "Date": "2026-07-08",
      "Scope": "Parser regex leading `**` made optional + duplicate lang-toggle removed",
      "Related Changes": "CHG-005",
      "Git Commit": "`4352dd4`",
      "Rollback Command": "`git revert 4352dd4`"
    },
    {
      "Checkpoint": "RB-006",
      "Date": "2026-07-08",
      "Scope": "SAT-001 MVP scope lock v0.1: DEC-003 + KANBAN → In Progress + LOG-004",
      "Related Changes": "CHG-006",
      "Git Commit": "`6fe4ce8`",
      "Rollback Command": "`git revert 6fe4ce8`"
    },
    {
      "Checkpoint": "RB-007",
      "Date": "2026-07-08",
      "Scope": "DEC-004 tech stack: single-file HTML + three.js CDN + raw CSS + vanilla JS",
      "Related Changes": "CHG-007",
      "Git Commit": "`c42a852`",
      "Rollback Command": "`git revert c42a852`"
    },
    {
      "Checkpoint": "RB-008",
      "Date": "2026-07-08",
      "Scope": "Phase 3 build kickoff: `mvp.html` v0.1 skeleton (4 tabs + three.js + atlas + orbit + sandbox)",
      "Related Changes": "CHG-008",
      "Git Commit": "`82e5748`",
      "Rollback Command": "`git revert 82e5748` + delete mvp.html"
    },
    {
      "Checkpoint": "RB-009",
      "Date": "2026-07-09",
      "Scope": "three.js CDN pin r147 (OrbitControls 404 on r160)",
      "Related Changes": "CHG-009",
      "Git Commit": "`2259a17`",
      "Rollback Command": "`git revert 2259a17`"
    },
    {
      "Checkpoint": "RB-010",
      "Date": "2026-07-09",
      "Scope": "jsdelivr primary CDN + crossorigin + better error HUD",
      "Related Changes": "CHG-010",
      "Git Commit": "`f449b4e`",
      "Rollback Command": "`git revert f449b4e`"
    },
    {
      "Checkpoint": "RB-011",
      "Date": "2026-07-09",
      "Scope": "i18n zh+EN toggle (59 keys, localStorage persist)",
      "Related Changes": "CHG-011",
      "Git Commit": "`ad36560`",
      "Rollback Command": "`git revert ad36560`"
    },
    {
      "Checkpoint": "RB-012",
      "Date": "2026-07-09",
      "Scope": "TDZ fix — hoist let declarations above setTab() first call",
      "Related Changes": "CHG-012",
      "Git Commit": "`558530f`",
      "Rollback Command": "`git revert 558530f`"
    },
    {
      "Checkpoint": "RB-013",
      "Date": "2026-07-09",
      "Scope": "Fix double-init + sandbox camera + lookAt(0,0,0)",
      "Related Changes": "CHG-013",
      "Git Commit": "`a21a739`",
      "Rollback Command": "`git revert a21a739`"
    },
    {
      "Checkpoint": "RB-014",
      "Date": "2026-07-09",
      "Scope": "Polish CubeSat realism + subsystem description panel",
      "Related Changes": "CHG-014",
      "Git Commit": "`decc23a`",
      "Rollback Command": "`git revert decc23a`"
    },
    {
      "Checkpoint": "RB-015",
      "Date": "2026-07-09",
      "Scope": "Polish round 2: atlas real data + i18n modal + live ISS",
      "Related Changes": "CHG-009 + CHG-010",
      "Git Commit": "`9892021`",
      "Rollback Command": "`git revert 9892021`"
    },
    {
      "Checkpoint": "RB-016",
      "Date": "2026-07-09",
      "Scope": "Realistic 1U CubeSat — 27 parts, corner rails, 4 antennas, star tracker, RBF, heaters",
      "Related Changes": "CHG-011",
      "Git Commit": "`4bfe835`",
      "Rollback Command": "`git revert 4bfe835`"
    },
    {
      "Checkpoint": "RB-017",
      "Date": "2026-07-09",
      "Scope": "Atlas modal 3D preview — 4 archetypes (ISS/Hubble/JWST/Starlink) + box + 1U",
      "Related Changes": "CHG-012",
      "Git Commit": "`320f8b3`",
      "Rollback Command": "`git revert 320f8b3`"
    },
    {
      "Checkpoint": "RB-018",
      "Date": "2026-07-09",
      "Scope": "Per-satellite distinct 3D models — ISS 6 modules + Canadarm, GPS L-wing, GOES ABI, JWST hexes, etc.",
      "Related Changes": "CHG-013",
      "Git Commit": "`7d270e3`",
      "Rollback Command": "`git revert 7d270e3`"
    },
    {
      "Checkpoint": "RB-019",
      "Date": "2026-07-09",
      "Scope": "GLB pipeline (GLTFLoader + GLTFExporter) + models/ + README",
      "Related Changes": "CHG-014",
      "Git Commit": "`ea216fd`",
      "Rollback Command": "`git revert ea216fd`"
    },
    {
      "Checkpoint": "RB-020",
      "Date": "2026-07-09",
      "Scope": "Polish round 3 — ISS Soyuz/Dragon docking, JWST mirror gaps, GOES magnetometer boom, modal 3-light",
      "Related Changes": "CHG-015",
      "Git Commit": "`a4d6321`",
      "Rollback Command": "`git revert a4d6321`"
    },
    {
      "Checkpoint": "RB-021",
      "Date": "2026-07-09",
      "Scope": "Orbit bands — altMin/altMax ranges, 2 boundary rings + translucent fill per orbit",
      "Related Changes": "CHG-016",
      "Git Commit": "`747453a`",
      "Rollback Command": "`git revert 747453a`"
    },
    {
      "Checkpoint": "RB-022",
      "Date": "2026-07-09",
      "Scope": "Orbit sample labels — sprite canvas pills with satellite names, sampleGroup auto-rotation",
      "Related Changes": "CHG-017",
      "Git Commit": "`dc9d03f`",
      "Rollback Command": "`git revert dc9d03f`"
    },
    {
      "Checkpoint": "RB-023",
      "Date": "2026-07-09",
      "Scope": "NASA reference photos in atlas modal — images-api.nasa.gov × 10",
      "Related Changes": "CHG-018",
      "Git Commit": "`dfb1831`",
      "Rollback Command": "`git revert dfb1831`"
    },
    {
      "Checkpoint": "RB-024",
      "Date": "2026-07-09",
      "Scope": "NASA photo 16:9 thumbnail + CHG-009..014 backfill entries",
      "Related Changes": "CHG-015",
      "Git Commit": "`9d330d2`",
      "Rollback Command": "`git revert 9d330d2`"
    },
    {
      "Checkpoint": "RB-025",
      "Date": "2026-07-09",
      "Scope": "Sandbox 3D reactive — all 5 dropdowns drive real 3D changes",
      "Related Changes": "CHG-016",
      "Git Commit": "`3a15ba8`",
      "Rollback Command": "`git revert 3a15ba8`"
    },
    {
      "Checkpoint": "RB-026",
      "Date": "2026-07-09",
      "Scope": "Sandbox OrbitControls (drag-rotate + scroll-zoom) + CHG-015/016 backfill",
      "Related Changes": "CHG-016b",
      "Git Commit": "`71be6b2`",
      "Rollback Command": "`git revert 71be6b2`"
    },
    {
      "Checkpoint": "RB-027",
      "Date": "2026-07-09",
      "Scope": "Sandbox budget breakdown — per-subsystem line items + sources",
      "Related Changes": "CHG-017",
      "Git Commit": "`c9d3de0`",
      "Rollback Command": "`git revert c9d3de0`"
    },
    {
      "Checkpoint": "RB-028",
      "Date": "2026-07-09",
      "Scope": "Budget breakdown tooltips — 14 hover tooltips (zh+en) explain how each number is derived",
      "Related Changes": "CHG-018",
      "Git Commit": "`374bd38`",
      "Rollback Command": "`git revert 374bd38`"
    }
  ],
  "rollback_levels": [
    {
      "level": "1",
      "title": "Content correction",
      "body": "Use when only wording, task status, or metadata is wrong.\n\nAction:\n- Edit the affected Markdown entry.\n- Add a new `CHG-*` entry explaining the correction."
    },
    {
      "level": "2",
      "title": "Single change rollback",
      "body": "Use when one implementation or content change should be undone.\n\nAction:\n- Use `git revert <commit-hash>` if the change was committed.\n- Update `ROLLBACK.md` with the rollback result.\n- Add a `LOGBOOK.md` entry.\n\n| RB-008 | 2026-07-08 | CHG-008 Phase 3 build kickoff: `mvp.html` v0.1 skeleton (4 tabs + three.js CubeSat + atlas cards + orbit rings + sandbox form) + DEC-005 inline subsystem taxonomy + SAT-006 → In Progress | CHG-008 | (this commit) | `git revert <this-commit>` + delete `mvp.html` |"
    },
    {
      "level": "3",
      "title": "Phase rollback",
      "body": "Use when a whole phase direction is rejected.\n\nAction:\n- Identify all `CHG-*` entries in that phase.\n- Revert their commits in reverse chronological order.\n- Move affected kanban tasks back to `Backlog` or `Next`.\n- Add a decision entry explaining why the phase was rolled back."
    }
  ],
  "counts": {
    "backlog": 6,
    "next": 2,
    "in_progress": 2,
    "review": 1,
    "done": 3,
    "phases": 6,
    "logbook": 6,
    "feedback": 2,
    "changes": 19,
    "decisions": 5,
    "checkpoints": 28
  }
}